CHANGES.rst
LICENSE.txt
MANIFEST.in
README
README.rst
setup.py
apiclient/__init__.py
apiclient/base.py
apiclient/ratelimiter.py
apiclient.egg-info/PKG-INFO
apiclient.egg-info/SOURCES.txt
apiclient.egg-info/dependency_links.txt
apiclient.egg-info/top_level.txt