Metadata-Version: 1.1
Name: apiclient
Version: 1.0.1
Summary: Framework for making good API client libraries using urllib3.
Home-page: https://github.com/shazow/apiclient
Author: Andrey Petrov
Author-email: andrey.petrov@shazow.net
License: MIT
Keywords: api client urllib3 keepalive threadsafe http rest
Platform: UNKNOWN
Classifier: Environment :: Web Environment
Classifier: Intended Audience :: Developers
Classifier: License :: OSI Approved :: MIT License
Classifier: Operating System :: OS Independent
Classifier: Programming Language :: Python
Classifier: Topic :: Internet :: WWW/HTTP
Classifier: Topic :: Software Development :: Libraries
Requires: urllib3
